rxutils/__init__.py
rxutils/terminal.py
rxutils-0.0.1.dist-info/METADATA
rxutils-0.0.1.dist-info/WHEEL
rxutils-0.0.1.dist-info/top_level.txt
rxutils-0.0.1.dist-info/RECORD
